rp_python_sdk/__init__.py
rp_python_sdk/endpoints/get_participants.py
rp_python_sdk/endpoints/pushed_authorisation_request.py
rp_python_sdk/endpoints/retrieve_tokens.py
rp_python_sdk/endpoints/user_info.py
rp_python_sdk/endpoints/util/fapi.py
rp_python_sdk/endpoints/util/mapping.py
rp_python_sdk/endpoints/util/system_info.py
rp_python_sdk/endpoints/util/user_agent.py
rp_python_sdk/endpoints/util/version_info.py
rp_python_sdk/filters/participant_filters.py
rp_python_sdk/model.py
rp_python_sdk/relying_party_client_sdk.py
rp_python_sdk/relying_party_client_sdk_exception.py
rp_python_sdk/sdk_config.py
rp_python_sdk/setup_logger.py
rp_python_sdk-1.1.7.dist-info/METADATA
rp_python_sdk-1.1.7.dist-info/WHEEL
rp_python_sdk-1.1.7.dist-info/RECORD
