Metadata-Version: 2.4
Name: rp_python_sdk
Version: 1.1.7
Summary: Python SDK for Relying Parties to enable simple integration with the Digital Identity ecosystem
License: Proprietary
Author: Erik Pragt
Author-email: erik.pragt@connectid.com.au
Requires-Python: >=3.12,<4.0
Classifier: License :: Other/Proprietary License
Classifier: Programming Language :: Python :: 3
Classifier: Programming Language :: Python :: 3.12
Classifier: Programming Language :: Python :: 3.13
Classifier: Programming Language :: Python :: 3.14
Requires-Dist: authlib (>=1.6.6,<2.0.0)
Requires-Dist: cffi (>=2.0.0,<3.0.0)
Requires-Dist: cryptography (>=46.0.2,<47.0.0)
Requires-Dist: joserfc (>=1.6.1,<2.0.0)
Requires-Dist: requests (>=2.32.5,<3.0.0)
Requires-Dist: urllib3 (>=2.6.3,<3.0.0)
